BuzzerboyAWSLightsailStack/ArchitectureMaker.py
BuzzerboyAWSLightsailStack/LightSailPostDeploy.py
BuzzerboyAWSLightsailStack/LightsailAIContainer.py
BuzzerboyAWSLightsailStack/LightsailBase.py
BuzzerboyAWSLightsailStack/LightsailBaseStandalone.py
BuzzerboyAWSLightsailStack/LightsailContainer.py
BuzzerboyAWSLightsailStack/LightsailContainerStandalone.py
BuzzerboyAWSLightsailStack/LightsailDatabase.py
BuzzerboyAWSLightsailStack/LightsailDatabaseStandalone.py
BuzzerboyAWSLightsailStack/LightsailFlags.py
BuzzerboyAWSLightsailStack/LightsailMixins.py
BuzzerboyAWSLightsailStack/__init__.py
buzzerboyawslightsail-0.334.1.dist-info/licenses/LICENSE
buzzerboyawslightsail-0.334.1.dist-info/METADATA
buzzerboyawslightsail-0.334.1.dist-info/WHEEL
buzzerboyawslightsail-0.334.1.dist-info/top_level.txt
buzzerboyawslightsail-0.334.1.dist-info/RECORD
