Metadata-Version: 2.4
Name: BuzzerboyAWSLightsail
Version: 0.334.1
Summary: Buzzerboy Architecture for Deploying Web Applications on AWS LightSail
Home-page: https://www.buzzerboy.com/
Author: Buzzerboy Inc
Author-email: Buzzerboy Inc <info@buzzerboy.com>
License: Copyright (c) 2024 Buzzerboy Inc. Canada. All Rights Reserved.
Project-URL: Homepage, https://www.buzzerboy.com/
Project-URL: Issues, https://dev.azure.com/buzzerboyinc/buzzerboy
Classifier: Programming Language :: Python :: 3
Classifier: License :: OSI Approved :: MIT License
Classifier: Operating System :: OS Independent
Requires-Python: >=3.8
License-File: LICENSE
Requires-Dist: cdktf<1.0,>=0.17.0
Requires-Dist: constructs<11.0,>=10.0.0
Requires-Dist: cdktf-cdktf-provider-aws>=12.0.0
Requires-Dist: cdktf-cdktf-provider-random>=8.0.0
Requires-Dist: toml
Requires-Dist: pipenv
Requires-Dist: boto3>=1.26.0
Requires-Dist: botocore>=1.29.0
Requires-Dist: BuzzerboyArchetype
Requires-Dist: AWSArchitectureBase
Dynamic: author
Dynamic: home-page
Dynamic: license-file
Dynamic: requires-dist
Dynamic: requires-python
